aiointerpreters/__init__.py
aiointerpreters/executors/__init__.py
aiointerpreters/executors/interpthread.py
aiointerpreters/runner.py
aiointerpreters/types.py
aiointerpreters-0.6.0.dist-info/WHEEL
aiointerpreters-0.6.0.dist-info/entry_points.txt
aiointerpreters-0.6.0.dist-info/METADATA
aiointerpreters-0.6.0.dist-info/RECORD
