Metadata-Version: 2.3
Name: aiointerpreters
Version: 0.6.0
Summary: Run CPU bound code with subinterpreters using asyncio.
Author: Jamie Chang
Author-email: Jamie Chang <jamie.cheng.chang@gmail.com>
License:                                  Apache License
Classifier: Development Status :: 4 - Beta
Classifier: Programming Language :: Python
Classifier: Programming Language :: Python :: 3.14
Requires-Python: >=3.14
Project-URL: HomePage, https://github.com/Jamie-Chang/aiointerpreters
